xtweet/__init__.py
xtweet/main.py
xtweet/media.py
xtweet/request.py
xtweet-1.0.2.dist-info/LICENSE
xtweet-1.0.2.dist-info/METADATA
xtweet-1.0.2.dist-info/WHEEL
xtweet-1.0.2.dist-info/top_level.txt
xtweet-1.0.2.dist-info/RECORD
