Metadata-Version: 2.1
Name: xtweet
Version: 1.0.2
Summary: Es una biblioteca que te permite interactuar de manera eficiente con la API de Twitter.
Home-page: https://github.com/fcoagz/pydolarvenezuela
Author: Francisco Griman
Author-email: Francisco Griman <grihardware@gmail.com>
License: MIT
Project-URL: Homepage, https://github.com/fcoagz/xtweet
Project-URL: Bug Tracker, https://github.com/fcoagz/xtweet/issues
Keywords: api,twitter,social media,data extraction,media download,python
Classifier: Programming Language :: Python :: 3
Classifier: License :: OSI Approved :: MIT License
Classifier: Operating System :: OS Independent
Requires-Python: >=3.8
License-File: LICENSE
Requires-Dist: requests
Requires-Dist: cachetools
